mcdp/__init__.py
mcdp/aio_stream.py
mcdp/command.py
mcdp/config.py
mcdp/context.py
mcdp/counter.py
mcdp/entities.py
mcdp/exceptions.py
mcdp/file_struct.py
mcdp/logger.py
mcdp/mcfunc.py
mcdp/mcstring.py
mcdp/typings.py
mcdp/variable.py
mcdp/version.py
Mcdp-0.1.2.dist-info/LICENSE
Mcdp-0.1.2.dist-info/METADATA
Mcdp-0.1.2.dist-info/WHEEL
Mcdp-0.1.2.dist-info/top_level.txt
Mcdp-0.1.2.dist-info/RECORD
